stanio/__init__.py
stanio/csv.py
stanio/json.py
stanio/py.typed
stanio/reshape.py
stanio-0.4.0.dist-info/LICENSE
stanio-0.4.0.dist-info/METADATA
stanio-0.4.0.dist-info/WHEEL
stanio-0.4.0.dist-info/top_level.txt
stanio-0.4.0.dist-info/RECORD
